{
    "CallerReference": "video-streaming-$(date +%s)",
    "Aliases": {
        "Quantity": 0
    },
    "DefaultRootObject": "index.html",
    "Origins": {
        "Quantity": 3,
        "Items": [
            {
                "Id": "API-Gateway",
                "DomainName": "4y3erwjgak.execute-api.us-east-1.amazonaws.com",
                "OriginPath": "/prod",
                "CustomHeaders": {
                    "Quantity": 0
                },
                "CustomOriginConfig": {
                    "HTTPPort": 80,
                    "HTTPSPort": 443,
                    "OriginProtocolPolicy": "https-only",
                    "OriginSslProtocols": {
                        "Quantity": 1,
                        "Items": [
                            "TLSv1.2"
                        ]
                    },
                    "OriginReadTimeout": 30,
                    "OriginKeepaliveTimeout": 5
                },
                "ConnectionAttempts": 3,
                "ConnectionTimeout": 10,
                "OriginShield": {
                    "Enabled": false
                },
                "OriginAccessControlId": ""
            },
            {
                "Id": "Videos-S3",
                "DomainName": "video-streaming-sstech-v3.s3.us-east-1.amazonaws.com",
                "OriginPath": "",
                "CustomHeaders": {
                    "Quantity": 0
                },
                "S3OriginConfig": {
                    "OriginAccessIdentity": ""
                },
                "ConnectionAttempts": 3,
                "ConnectionTimeout": 10,
                "OriginShield": {
                    "Enabled": false
                },
                "OriginAccessControlId": "E7EJ03JHTNEFJ"
            },
            {
                "Id": "Frontend-S3",
                "DomainName": "video-streaming-frontend-v3.s3.us-east-1.amazonaws.com",
                "OriginPath": "",
                "CustomHeaders": {
                    "Quantity": 0
                },
                "S3OriginConfig": {
                    "OriginAccessIdentity": ""
                },
                "ConnectionAttempts": 3,
                "ConnectionTimeout": 10,
                "OriginShield": {
                    "Enabled": false
                },
                "OriginAccessControlId": "E22CW97T3Q858S"
            }
        ]
    },
    "OriginGroups": {
        "Quantity": 0
    },
    "DefaultCacheBehavior": {
        "TargetOriginId": "Frontend-S3",
        "TrustedSigners": {
            "Enabled": false,
            "Quantity": 0
        },
        "TrustedKeyGroups": {
            "Enabled": false,
            "Quantity": 0
        },
        "ViewerProtocolPolicy": "redirect-to-https",
        "AllowedMethods": {
            "Quantity": 3,
            "Items": [
                "HEAD",
                "GET",
                "OPTIONS"
            ],
            "CachedMethods": {
                "Quantity": 2,
                "Items": [
                    "HEAD",
                    "GET"
                ]
            }
        },
        "SmoothStreaming": false,
        "Compress": true,
        "LambdaFunctionAssociations": {
            "Quantity": 0
        },
        "FunctionAssociations": {
            "Quantity": 0
        },
        "FieldLevelEncryptionId": "",
        "ResponseHeadersPolicyId": "8c33d61f-b4c4-4cc1-8d8d-6a33d0e1f073",
        "ForwardedValues": {
            "QueryString": false,
            "Cookies": {
                "Forward": "none"
            },
            "Headers": {
                "Quantity": 0
            },
            "QueryStringCacheKeys": {
                "Quantity": 0
            }
        },
        "MinTTL": 0,
        "DefaultTTL": 86400,
        "MaxTTL": 31536000
    },
    "CacheBehaviors": {
        "Quantity": 2,
        "Items": [
            {
                "PathPattern": "/api/*",
                "TargetOriginId": "API-Gateway",
                "TrustedSigners": {
                    "Enabled": false,
                    "Quantity": 0
                },
                "TrustedKeyGroups": {
                    "Enabled": false,
                    "Quantity": 0
                },
                "ViewerProtocolPolicy": "https-only",
                "AllowedMethods": {
                    "Quantity": 7,
                    "Items": [
                        "HEAD",
                        "DELETE",
                        "POST",
                        "GET",
                        "OPTIONS",
                        "PUT",
                        "PATCH"
                    ],
                    "CachedMethods": {
                        "Quantity": 2,
                        "Items": [
                            "HEAD",
                            "GET"
                        ]
                    }
                },
                "SmoothStreaming": false,
                "Compress": false,
                "LambdaFunctionAssociations": {
                    "Quantity": 0
                },
                "FunctionAssociations": {
                    "Quantity": 0
                },
                "FieldLevelEncryptionId": "",
                "CachePolicyId": "4135ea2d-6df8-44a3-9df3-4b5a84be39ad",
                "OriginRequestPolicyId": "88a5eaf4-2fd4-4709-b370-b4c650ea3fcf"
            },
            {
                "PathPattern": "/uploads/*",
                "TargetOriginId": "Videos-S3",
                "TrustedSigners": {
                    "Enabled": false,
                    "Quantity": 0
                },
                "TrustedKeyGroups": {
                    "Enabled": false,
                    "Quantity": 0
                },
                "ViewerProtocolPolicy": "https-only",
                "AllowedMethods": {
                    "Quantity": 3,
                    "Items": [
                        "HEAD",
                        "GET",
                        "OPTIONS"
                    ],
                    "CachedMethods": {
                        "Quantity": 2,
                        "Items": [
                            "HEAD",
                            "GET"
                        ]
                    }
                },
                "SmoothStreaming": false,
                "Compress": false,
                "LambdaFunctionAssociations": {
                    "Quantity": 0
                },
                "FunctionAssociations": {
                    "Quantity": 0
                },
                "FieldLevelEncryptionId": "",
                "ForwardedValues": {
                    "QueryString": false,
                    "Cookies": {
                        "Forward": "none"
                    },
                    "Headers": {
                        "Quantity": 0
                    },
                    "QueryStringCacheKeys": {
                        "Quantity": 0
                    }
                },
                "MinTTL": 0,
                "DefaultTTL": 3600,
                "MaxTTL": 86400
            }
        ]
    },
    "CustomErrorResponses": {
        "Quantity": 1,
        "Items": [
            {
                "ErrorCode": 404,
                "ResponsePagePath": "/index.html",
                "ResponseCode": "200",
                "ErrorCachingMinTTL": 300
            }
        ]
    },
    "Comment": "Video Streaming SStech v3.0 - Complete Integration",
    "Logging": {
        "Enabled": false,
        "IncludeCookies": false,
        "Bucket": "",
        "Prefix": ""
    },
    "PriceClass": "PriceClass_All",
    "Enabled": false,
    "ViewerCertificate": {
        "CloudFrontDefaultCertificate": false,
        "ACMCertificateArn": "arn:aws:acm:us-east-1:969430605054:certificate/e9e3a86e-39ce-4b27-91fd-3e8f21a3dcc5",
        "SSLSupportMethod": "sni-only",
        "MinimumProtocolVersion": "TLSv1.2_2021",
        "Certificate": "arn:aws:acm:us-east-1:969430605054:certificate/e9e3a86e-39ce-4b27-91fd-3e8f21a3dcc5",
        "CertificateSource": "acm"
    },
    "Restrictions": {
        "GeoRestriction": {
            "RestrictionType": "none",
            "Quantity": 0
        }
    },
    "WebACLId": "",
    "HttpVersion": "http2",
    "IsIPV6Enabled": true,
    "ContinuousDeploymentPolicyId": "",
    "Staging": false
}